furiosa_llm_models/__init__.py
furiosa_llm_models/paged_attention.md
furiosa_llm_models/bert/__init__.py
furiosa_llm_models/bert/huggingface.py
furiosa_llm_models/bert/huggingface_unsplit.py
furiosa_llm_models/bert/huggingface_unsplit_packed.py
furiosa_llm_models/bert/symbolic/__init__.py
furiosa_llm_models/bert/symbolic/huggingface.py
furiosa_llm_models/bert/symbolic/huggingface_rngd_gelu.py
furiosa_llm_models/bert/symbolic/huggingface_unsplit.py
furiosa_llm_models/bert/symbolic/mlperf_submission.py
furiosa_llm_models/bert/symbolic/experimental/__init__.py
furiosa_llm_models/bert/symbolic/experimental/huggingface_unsplit_packed.py
furiosa_llm_models/encoders/__init__.py
furiosa_llm_models/encoders/bert_encoder.py
furiosa_llm_models/encoders/encoder.py
furiosa_llm_models/generators/__init__.py
furiosa_llm_models/generators/generator.py
furiosa_llm_models/generators/mlperf_submission_generator_mcp.py
furiosa_llm_models/generators/mlperf_submission_generator_mcp_non_slice.py
furiosa_llm_models/generators/packing.py
furiosa_llm_models/generators/paged_attention_generator.py
furiosa_llm_models/generators/paged_attention_optimized_generator.py
furiosa_llm_models/generators/paged_attention_optimized_generator_beam_search.py
furiosa_llm_models/generators/paged_attention_optimized_generator_beam_search_optimized.py
furiosa_llm_models/generators/paged_attention_optimized_generator_non_slice.py
furiosa_llm_models/generators/specdec_generator.py
furiosa_llm_models/generators/symbolic/__init__.py
furiosa_llm_models/generators/symbolic/bert_generator.py
furiosa_llm_models/generators/symbolic/llama_multi_gpu_paged_attention_optimized_generator.py
furiosa_llm_models/generators/symbolic/llama_multi_gpu_paged_attention_optimized_generator_mcp.py
furiosa_llm_models/generators/symbolic/quant_paged_attention_generator.py
furiosa_llm_models/generators/symbolic/quant_preallocated_concat_generator.py
furiosa_llm_models/generators/v2/__init__.py
furiosa_llm_models-2025.3.0.dist-info/WHEEL
furiosa_llm_models-2025.3.0.dist-info/METADATA
furiosa_llm_models-2025.3.0.dist-info/RECORD
