Metadata-Version: 2.1
Name: furiosa-llm-models
Version: 2025.3.0
Summary: Furiosa LLM
Author-email: "FuriosaAI Inc." <pkg@furiosa.ai>
Requires-Python: ~=3.8
Classifier: License :: OSI Approved :: Apache Software License
Classifier: Programming Language :: Python :: 3
Classifier: Programming Language :: Python :: 3.8
Classifier: Programming Language :: Python :: 3.9
Classifier: Programming Language :: Python :: 3.10
Classifier: Topic :: Software Development :: Libraries :: Python Modules
Classifier: Topic :: Scientific/Engineering :: Artificial Intelligence
Requires-Dist: PyYAML
Requires-Dist: numpy<2
Requires-Dist: transformers==4.48.1
Requires-Dist: torch==2.5.1
Requires-Dist: evaluate==0.4.2 ; extra == "e2e_test"
Requires-Dist: scipy~=1.10.1 ; extra == "e2e_test"
Requires-Dist: nltk~=3.8.1 ; extra == "e2e_test"
Requires-Dist: absl-py~=2.1.0 ; extra == "e2e_test"
Requires-Dist: rouge_score~=0.1.2 ; extra == "e2e_test"
Requires-Dist: pytest ; extra == "test"
Requires-Dist: ruff ; extra == "test"
Requires-Dist: sentencepiece~=0.2.0 ; extra == "test"
Provides-Extra: e2e_test
Provides-Extra: test
